dpmmpython/__init__.py
dpmmpython/dpmmwrapper.py
dpmmpython/install.py
dpmmpython/priors.py
dpmmpython/release.py
dpmmpython_trax-0.1.5.dist-info/LICENSE
dpmmpython_trax-0.1.5.dist-info/METADATA
dpmmpython_trax-0.1.5.dist-info/WHEEL
dpmmpython_trax-0.1.5.dist-info/pbr.json
dpmmpython_trax-0.1.5.dist-info/top_level.txt
dpmmpython_trax-0.1.5.dist-info/RECORD
